vlm_pypoke/__init__.py
vlm_pypoke/client.py
vlm_pypoke/error.py
vlm_pypoke-0.3.1.dist-info/METADATA
vlm_pypoke-0.3.1.dist-info/WHEEL
vlm_pypoke-0.3.1.dist-info/top_level.txt
vlm_pypoke-0.3.1.dist-info/RECORD
